input_detect/__init__.py
input_detect-1.0.2.dist-info/METADATA
input_detect-1.0.2.dist-info/WHEEL
input_detect-1.0.2.dist-info/top_level.txt
input_detect-1.0.2.dist-info/RECORD
